Metadata-Version: 2.1
Name: package-model
Version: 0.3
Summary: Compute the square of a number
Home-page: UNKNOWN
Author: Lorenzo Marini
License: UNKNOWN
Project-URL: GitHub, https://github.com/lorenzomarini96/package_model
Project-URL: Documentation, https://github.com/lorenzomarini96/package_model
Platform: UNKNOWN
Classifier: License :: OSI Approved :: GNU General Public License v3 or later (GPLv3+)
Classifier: Programming Language :: Python :: 3
Classifier: Programming Language :: Python :: 3.8
License-File: LICENSE
